microcrypta/__init__.py
microcrypta/account.py
microcrypta/backtest.py
microcrypta/bsh.py
microcrypta/coin.py
microcrypta/coinmarket.py
microcrypta/config.py
tests/__init__.py
tests/test_account.py
tests/test_backtest.py
tests/test_bsh.py
tests/test_coin.py
tests/test_coinmarket.py
microcrypta-0.1.1.dist-info/METADATA
microcrypta-0.1.1.dist-info/WHEEL
microcrypta-0.1.1.dist-info/top_level.txt
microcrypta-0.1.1.dist-info/RECORD
