Metadata-Version: 2.1
Name: microcrypta
Version: 0.1.1
Summary: A micro package for cryptocurrency technical analysis
Home-page: https://github.com/bcivitcioglu/microcrypta
Author: Burak Ç.
Author-email: bcivitcioglu@gmail.com
Classifier: Programming Language :: Python :: 3
Classifier: License :: OSI Approved :: MIT License
Classifier: Operating System :: OS Independent
Requires-Python: >=3.6
Requires-Dist: ccxt
Requires-Dist: pandas
Requires-Dist: numpy
Requires-Dist: matplotlib
Requires-Dist: mplfinance
Requires-Dist: seaborn
Requires-Dist: tqdm
